Metadata-Version: 2.1
Name: matpack
Version: 1.0.6
Summary: pacote de funções matemáticas únicas
Home-page: UNKNOWN
Author: Thiarly Souza
Author-email: Thiarly@ufrn.edu.br
License: MIT
Keywords: matematica,funções
Platform: UNKNOWN
License-File: LICENSE.txt
